gmft_local/__future__init__.py
gmft_local/__init__.py
gmft_local/_dataclasses.py
gmft_local/auto.py
gmft_local/common.py
gmft_local/presets.py
gmft_local/table_captioning.py
gmft_local/table_detection.py
gmft_local/table_function.py
gmft_local/table_function_algorithm.py
gmft_local/table_visualization.py
gmft_local/_rich_text/__init__.py
gmft_local/_rich_text/common.py
gmft_local/_rich_text/rich_page.py
gmft_local/algo/__init__.py
gmft_local/algo/dividers.py
gmft_local/algo/histogram.py
gmft_local/detectors/common.py
gmft_local/detectors/img2table.py
gmft_local/detectors/tatr.py
gmft_local/formatters/common.py
gmft_local/formatters/ditr.py
gmft_local/formatters/histogram.py
gmft_local/formatters/tatr.py
gmft_local/formatters/with_img2table.py
gmft_local/formatters/with_tabled.py
gmft_local/pdf_bindings/__init__.py
gmft_local/pdf_bindings/bindings_pdfium.py
gmft_local/pdf_bindings/common.py
gmft_local/pdf_bindings/pdfium.py
gmft_local-0.4.0.dist-info/LICENSE
gmft_local-0.4.0.dist-info/WHEEL
gmft_local-0.4.0.dist-info/METADATA
gmft_local-0.4.0.dist-info/RECORD
