Metadata-Version: 2.3
Name: gmft_local
Version: 0.4.0
Summary: Lightweight, performant, deep table extraction
Author: conjunct, conjuncts
Requires-Python: >=3.9
Classifier: Development Status :: 4 - Beta
Classifier: License :: OSI Approved :: MIT License
Requires-Dist: pypdfium2 >= 4
Requires-Dist: transformers >= 4.35.2
Requires-Dist: torch
Requires-Dist: pillow
Requires-Dist: pandas
Requires-Dist: matplotlib
Requires-Dist: tabulate
Requires-Dist: pymupdf ; extra == "pymupdf"
Requires-Dist: tabled-pdf >= 0.1.4 ; extra == "tabled"
Project-URL: Homepage, https://github.com/conjuncts/gmft
Project-URL: Issues, https://github.com/conjuncts/gmft/issues
Provides-Extra: pymupdf
Provides-Extra: tabled
